CHANGES.txt
LICENSE.txt
MANIFEST.in
README.rst
setup.cfg
setup.py
pwrentch/__init__.py
pwrentch.FileReferences.egg-info/PKG-INFO
pwrentch.FileReferences.egg-info/SOURCES.txt
pwrentch.FileReferences.egg-info/dependency_links.txt
pwrentch.FileReferences.egg-info/entry_points.txt
pwrentch.FileReferences.egg-info/namespace_packages.txt
pwrentch.FileReferences.egg-info/not-zip-safe
pwrentch.FileReferences.egg-info/paster_plugins.txt
pwrentch.FileReferences.egg-info/requires.txt
pwrentch.FileReferences.egg-info/top_level.txt
pwrentch/FileReferences/README.txt
pwrentch/FileReferences/__init__.py
pwrentch/FileReferences/config.py
pwrentch/FileReferences/configure.zcml
pwrentch/FileReferences/browser/__init__.py
pwrentch/FileReferences/browser/configure.zcml
pwrentch/FileReferences/browser/file_references.py
pwrentch/FileReferences/browser/reference_list.pt
pwrentch/FileReferences/content/__init__.py
pwrentch/FileReferences/content/configure.zcml
pwrentch/FileReferences/interfaces/__init__.py
pwrentch/FileReferences/portlets/__init__.py
pwrentch/FileReferences/portlets/configure.zcml
pwrentch/FileReferences/profiles/default/factorytool.xml
pwrentch/FileReferences/profiles/default/metadata.xml
pwrentch/FileReferences/profiles/default/portlets.xml
pwrentch/FileReferences/profiles/default/types.xml
pwrentch/FileReferences/static/filereferences.css
pwrentch/FileReferences/static/filereferences.js
pwrentch/FileReferences/tests/__init__.py
pwrentch/FileReferences/tests/base.py
pwrentch/FileReferences/tests/test_doctest.py