Metadata-Version: 1.1
Name: pwrentch.FileReferences
Version: 1.0.3
Summary: Lists file and image items and the items that link to them
Home-page: https://github.com/paulrentschler/pwrentch.FileReferences
Author: Paul Rentschler
Author-email: paul@rentschler.ws
License: GPL
Keywords: Plone FileReferences
Platform: UNKNOWN
Classifier: Programming Language :: Python
Classifier: License :: OSI Approved :: GNU General Public License (GPL)
Classifier: Framework :: Plone
Classifier: Framework :: Plone :: 4.1
